[{"Nombre":"Nuggets","Fechavencimiento":"2023-08-11T00:00:00-03:00","Precio":4999.122,"Tamanio":"Mediano"},{"Nombre":"Tarta","Fechavencimiento":"2022-09-12T00:00:00-03:00","Precio":3428.6145,"Tamanio":"Mediano"},{"Nombre":"Hamburguesa","Fechavencimiento":"2023-06-20T00:00:00-03:00","Precio":3443.1785,"Tamanio":"Mediano"},{"Nombre":"Hamburguesa","Fechavencimiento":"2025-02-19T00:00:00-03:00","Precio":1179.3544,"Tamanio":"Mediano"},{"Nombre":"Tarta","Fechavencimiento":"2024-09-09T00:00:00-03:00","Precio":2467.656,"Tamanio":"Mediano"},{"Nombre":"Lomo","Fechavencimiento":"2023-07-30T00:00:00-03:00","Precio":1013.5609,"Tamanio":"Mediano"},{"Nombre":"Merluza","Fechavencimiento":"2023-08-18T00:00:00-03:00","Precio":2065.151,"Tamanio":"Chico"}]
